aegis_research/__init__.py
aegis_research/exceptions.py
aegis_research/models.py
aegis_research-0.1.1.dist-info/METADATA
aegis_research-0.1.1.dist-info/WHEEL
aegis_research-0.1.1.dist-info/licenses/LICENSE
aegis_research-0.1.1.dist-info/RECORD
