Metadata-Version: 2.4
Name: aegis-research
Version: 0.1.1
Summary: Python SDK for Aegis Research API - AI-powered web research as a service
Project-URL: Homepage, https://aegisagent.ai/research
Project-URL: Documentation, https://aegisagent.ai/api-docs
Project-URL: Repository, https://github.com/aegis-agent/aegis-research-sdk
Project-URL: Changelog, https://github.com/aegis-agent/aegis-research-sdk/blob/main/CHANGELOG.md
Author-email: Aegis <aegis@richardbankole.com>
License-Expression: MIT
License-File: LICENSE
Keywords: aegis,ai,api,llm,research,web-research
Classifier: Development Status :: 4 - Beta
Classifier: Intended Audience :: Developers
Classifier: License :: OSI Approved :: MIT License
Classifier: Programming Language :: Python :: 3
Classifier: Programming Language :: Python :: 3.9
Classifier: Programming Language :: Python :: 3.10
Classifier: Programming Language :: Python :: 3.11
Classifier: Programming Language :: Python :: 3.12
Classifier: Topic :: Internet :: WWW/HTTP
Classifier: Topic :: Scientific/Engineering :: Artificial Intelligence
Requires-Python: >=3.9
Requires-Dist: httpx>=0.24.0
Provides-Extra: dev
Requires-Dist: pytest-asyncio>=0.21; extra == 'dev'
Requires-Dist: pytest>=7.0; extra == 'dev'
Requires-Dist: python-dotenv>=1.0; extra == 'dev'
